ssh_ca_client/__init__.py
ssh_ca_client/__main__.py
ssh_ca_client/cli.py
ssh_ca_client/config.py
ssh_ca_client/server.py
ssh_ca_client/ssh.py
ca_client-0.1.0.dist-info/top_level.txt
ca_client-0.1.0.dist-info/entry_points.txt
ca_client-0.1.0.dist-info/METADATA
ca_client-0.1.0.dist-info/DESCRIPTION.rst
ca_client-0.1.0.dist-info/metadata.json
ca_client-0.1.0.dist-info/WHEEL
ca_client-0.1.0.dist-info/RECORD
