Metadata-Version: 2.0
Name: ca-client
Version: 0.1.0
Summary: SSH CA Client
Home-page: https://github.com/commercehub-oss/ssh-ca-client
Author: CommerceHub
Author-email: UNKNOWN
License: UNKNOWN
Platform: UNKNOWN
Classifier: Programming Language :: Python :: 2.7
Classifier: Programming Language :: Python :: 3.2
Classifier: Programming Language :: Python :: 3.3
Classifier: Programming Language :: Python :: 3.4
Classifier: Programming Language :: Python :: 3.5
Classifier: Programming Language :: Python :: 3.4
Classifier: Programming Language :: Python :: 3.5
Requires-Dist: argparse (>=1.1)
Requires-Dist: requests (>=2.13.0)
